{
  "title": "ตัวแปลงไฟล์",
  "description": "อนุญาตให้ไฟล์แปลเป็นรูปภาพหรือประเภทเนื้อหาข้อความ",
  "version": "1.0.2.0",
  "author": "Monkey",
  "guid": "04c4d099-530e-432d-b107-3b0696b980cf",
  "readmeUrl": "https://raw.githubusercontent.com/monkeypaste/FileConverter/master/README.md",
  "projectUrl": "https://github.com/monkeypaste/FileConverter",
  "packageUrl": "https://github.com/monkeypaste/FileConverter/releases/download/v1.0.0/FileConverter.zip",
  "iconUri": "https://raw.githubusercontent.com/monkeypaste/FileConverter/master/icon.png",
  "tags": "core, text, image, file, converter, file to text, file to image",
  "packageType": "Dll",
  "analyzer": {
    "inputType": {
      "file": true
    },
    "outputType": {
      "image": true,
      "text": true
    },
    "parameters": [
      {
        "label": "ไฟล์เพื่อแปลง",
        "description": "",
        "controlType": "TextBox",
        "unitType": "RawDataContentQuery",
        "isVisible": false,
        "paramId": 1,
        "values": [
          {
            "value": "{ClipText}"
          }
        ]
      },
      {
        "label": "ประเภทเอาต์พุต",
        "description": "เฉพาะ. png หรือ .txt ตอนนี้",
        "controlType": "ComboBox",
        "unitType": "PlainText",
        "isRequired": true,
        "paramId": 2,
        "values": [
          {
            "label": "ข้อความ",
            "value": "Text",
            "isDefault": true
          },
          {
            "label": "ภาพ",
            "value": "Image"
          }
        ]
      }
    ],
    "presets": [
      {
        "guid": "2159a492-cdc5-429d-bf26-08c478f87e52",
        "label": "แปลงเป็นข้อความ",
        "iconUri": "text.png",
        "description": "ความพยายามในการแปลงไฟล์ที่ให้เป็นข้อความธรรมดา",
        "values": [
          {
            "paramId": 2,
            "value": "Text"
          }
        ]
      },
      {
        "guid": "c24df3c2-5316-45e2-aac4-ffccdf8a8460",
        "iconUri": "image.png",
        "label": "แปลงเป็นรูปภาพ",
        "description": "ความพยายามในการแปลงไฟล์ที่ให้เป็นภาพในหน่วยความจำ",
        "values": [
          {
            "paramId": 2,
            "value": "Image"
          }
        ]
      }
    ]
  }
}